[
   {
      "orderNo":"nw-781296-84397233-2526104",
      "date":"1/14/2019",
      "customer":"Scudder Strategic Municiple Income Trust",
      "trackingNo":"TP-905595-90370704-8538696",
      "status":"'Shipped'",
      "consignee":"Oramed Pharmaceuticals Inc."
   },
   {
      "orderNo":"gn-080407-04603810-2459572",
      "date":"1/16/2019",
      "customer":"M III Acquisition Corp.",
      "trackingNo":"TP-610179-24801524-3416429",
      "status":"'Shipped'",
      "consignee":"Teleflex Incorporated"
   },
   {
      "orderNo":"cq-448782-99078589-8292888",
      "date":"11/17/2018",
      "customer":"Mellanox Technologies, Ltd.",
      "trackingNo":"TP-050244-16875943-1311692",
      "status":"'Delivered'",
      "consignee":"Onvia, Inc."
   },
   {
      "orderNo":"ko-170382-00699724-6588291",
      "date":"5/10/2019",
      "customer":"TICC Capital Corp.",
      "trackingNo":"TP-726572-89278233-2039726",
      "status":"'In Transit'",
      "consignee":"Swift Transportation Company"
   },
   {
      "orderNo":"ie-967830-00585506-4403067",
      "date":"10/25/2018",
      "customer":"ArQule, Inc.",
      "trackingNo":"TP-645972-89894243-7458083",
      "status":"'In Transit'",
      "consignee":"Peoples Bancorp of North Carolina, Inc."
   },
   {
      "orderNo":"di-517041-82125743-0756015",
      "date":"7/26/2019",
      "customer":"AVX Corporation",
      "trackingNo":"TP-422472-90219609-4174768",
      "status":"'In Transit'",
      "consignee":"DarioHealth Corp."
   },
   {
      "orderNo":"ho-575434-97018308-1012913",
      "date":"6/25/2019",
      "customer":"Matlin & Partners Acquisition Corporation",
      "trackingNo":"TP-417250-73689999-8755259",
      "status":"'In Transit'",
      "consignee":"CorEnergy Infrastructure Trust, Inc."
   },
   {
      "orderNo":"gn-481722-16862182-5891315",
      "date":"12/15/2018",
      "customer":"Voya Emerging Markets High Income Dividend Equity Fund",
      "trackingNo":"TP-275723-92298450-8969968",
      "status":"'In Transit'",
      "consignee":"Advanced Disposal Services, Inc."
   },
   {
      "orderNo":"ic-935192-67556690-5583991",
      "date":"11/1/2018",
      "customer":"Suncor Energy  Inc.",
      "trackingNo":"TP-173274-62356185-3437582",
      "status":"'Shipped'",
      "consignee":"OneMain Holdings, Inc."
   },
   {
      "orderNo":"kc-753180-55998002-8885296",
      "date":"10/12/2019",
      "customer":"Bear State Financial, Inc.",
      "trackingNo":"TP-114900-89022453-9135673",
      "status":"'In Transit'",
      "consignee":"Caterpillar, Inc."
   },
   {
      "orderNo":"ms-736210-00760555-9898849",
      "date":"6/27/2019",
      "customer":"Saban Capital Acquisition Corp.",
      "trackingNo":"TP-359563-53718067-4975617",
      "status":"'In Transit'",
      "consignee":"Brookdale Senior Living Inc."
   },
   {
      "orderNo":"on-114900-71547150-0544454",
      "date":"9/21/2019",
      "customer":"MainStay DefinedTerm Municipal Opportunities Fund",
      "trackingNo":"TP-769436-07303038-8243925",
      "status":"'Delivered'",
      "consignee":"Twin Disc, Incorporated"
   },
   {
      "orderNo":"sq-853693-44078136-4811787",
      "date":"3/27/2019",
      "customer":"America's Car-Mart, Inc.",
      "trackingNo":"TP-630590-20877821-7895357",
      "status":"'In Transit'",
      "consignee":"Nuveen S&P 500 Dynamic Overwrite Fund"
   },
   {
      "orderNo":"mj-412371-86386675-4517971",
      "date":"4/18/2019",
      "customer":"National Western Life Group, Inc.",
      "trackingNo":"TP-192808-61860167-6289104",
      "status":"'Delivered'",
      "consignee":"AMREP Corporation"
   },
   {
      "orderNo":"eg-172671-91768620-0079970",
      "date":"6/2/2019",
      "customer":"Visa Inc.",
      "trackingNo":"TP-446838-33463331-1283917",
      "status":"'In Transit'",
      "consignee":"Ciner Resources LP"
   },
   {
      "orderNo":"tv-562978-76355144-1249414",
      "date":"10/26/2018",
      "customer":"Intrawest Resorts Holdings, Inc.",
      "trackingNo":"TP-579384-25996443-7394823",
      "status":"'Delivered'",
      "consignee":"Ultragenyx Pharmaceutical Inc."
   },
   {
      "orderNo":"ir-191114-39481485-0994968",
      "date":"6/4/2019",
      "customer":"Shutterfly, Inc.",
      "trackingNo":"TP-556265-46492830-8527807",
      "status":"'Delivered'",
      "consignee":"Impinj, Inc."
   },
   {
      "orderNo":"tu-135851-74828929-8061375",
      "date":"8/15/2019",
      "customer":"Western Asset Managed Municipals Fund, Inc.",
      "trackingNo":"TP-677445-82173949-2040417",
      "status":"'In Transit'",
      "consignee":"Ekso Bionics Holdings, Inc."
   },
   {
      "orderNo":"hz-862881-53025754-0363608",
      "date":"7/17/2019",
      "customer":"InVivo Therapeutics Holdings Corp.",
      "trackingNo":"TP-078524-70595916-3339589",
      "status":"'Shipped'",
      "consignee":"Choice Hotels International, Inc."
   },
   {
      "orderNo":"ba-725671-91947158-0885968",
      "date":"6/15/2019",
      "customer":"ABIOMED, Inc.",
      "trackingNo":"TP-821361-69079768-6207747",
      "status":"'Delivered'",
      "consignee":"AVEO Pharmaceuticals, Inc."
   },
   {
      "orderNo":"wv-682420-65104598-9543998",
      "date":"1/16/2019",
      "customer":"Nuven Mortgage Opportunity Term Fund 2",
      "trackingNo":"TP-990893-76020222-3061186",
      "status":"'Delivered'",
      "consignee":"Immune Design Corp."
   },
   {
      "orderNo":"dc-168061-05106023-5431705",
      "date":"5/12/2019",
      "customer":"American Vanguard Corporation",
      "trackingNo":"TP-927228-99969535-3844186",
      "status":"'Shipped'",
      "consignee":"Kronos Worldwide Inc"
   },
   {
      "orderNo":"yu-095812-17311608-4932797",
      "date":"3/4/2019",
      "customer":"Motorola Solutions, Inc.",
      "trackingNo":"TP-528797-98677340-2419074",
      "status":"'Shipped'",
      "consignee":"Bazaarvoice, Inc."
   },
   {
      "orderNo":"pg-709802-58190681-5221388",
      "date":"3/16/2019",
      "customer":"General Finance Corporation",
      "trackingNo":"TP-765907-87627307-3632546",
      "status":"'Delivered'",
      "consignee":"John Hancock Income Securities Trust"
   },
   {
      "orderNo":"wi-125091-16647874-5809857",
      "date":"10/5/2019",
      "customer":"Global X Yieldco Index ETF",
      "trackingNo":"TP-638074-62057947-6680752",
      "status":"'Delivered'",
      "consignee":"Tennessee Valley Authority"
   },
   {
      "orderNo":"hf-001680-02287565-3336000",
      "date":"11/2/2018",
      "customer":"Liberty Media Corporation",
      "trackingNo":"TP-434447-40930103-2301527",
      "status":"'In Transit'",
      "consignee":"Customers Bancorp, Inc"
   },
   {
      "orderNo":"cc-944457-96382813-1679724",
      "date":"9/29/2019",
      "customer":"Sotheby's",
      "trackingNo":"TP-578989-89491808-8357145",
      "status":"'Delivered'",
      "consignee":"First Trust SSI Strategic Convertible Securities ETF"
   },
   {
      "orderNo":"xt-021272-62357626-7134069",
      "date":"5/3/2019",
      "customer":"TCP Capital Corp.",
      "trackingNo":"TP-909305-41829556-7531446",
      "status":"'Delivered'",
      "consignee":"Aware, Inc."
   },
   {
      "orderNo":"xk-495764-60132066-6034275",
      "date":"11/16/2018",
      "customer":"Costamare Inc.",
      "trackingNo":"TP-853421-37348459-3024848",
      "status":"'In Transit'",
      "consignee":"XOMA Corporation"
   },
   {
      "orderNo":"ef-401222-88152002-4476803",
      "date":"2/14/2019",
      "customer":"RiceBran Technologies",
      "trackingNo":"TP-291653-21346800-6697798",
      "status":"'Shipped'",
      "consignee":"CafePress Inc."
   },
   {
      "orderNo":"fm-978901-19143577-7259684",
      "date":"4/6/2019",
      "customer":"Vail Resorts, Inc.",
      "trackingNo":"TP-942231-96168383-2320526",
      "status":"'Delivered'",
      "consignee":"First Trust MLP and Energy Income Fund"
   },
   {
      "orderNo":"pa-228847-07329853-7786624",
      "date":"6/29/2019",
      "customer":"FIRST REPUBLIC BANK",
      "trackingNo":"TP-704148-44589305-5481237",
      "status":"'Delivered'",
      "consignee":"Edge Therapeutics, Inc."
   },
   {
      "orderNo":"pm-797577-72382341-0686892",
      "date":"2/17/2019",
      "customer":"Nova Measuring Instruments Ltd.",
      "trackingNo":"TP-441910-42303095-3785571",
      "status":"'Shipped'",
      "consignee":"Telephone and Data Systems, Inc."
   },
   {
      "orderNo":"rj-264589-64163132-4916191",
      "date":"6/24/2019",
      "customer":"MediWound Ltd.",
      "trackingNo":"TP-602726-45102729-9013823",
      "status":"'In Transit'",
      "consignee":"Swiss Helvetia Fund, Inc. (The)"
   },
   {
      "orderNo":"lr-807401-03596253-3650550",
      "date":"6/12/2019",
      "customer":"Andina Acquisition Corp. II",
      "trackingNo":"TP-520275-61700216-2116580",
      "status":"'In Transit'",
      "consignee":"Essent Group Ltd."
   },
   {
      "orderNo":"qf-755686-14323123-3580933",
      "date":"6/23/2019",
      "customer":"Capitala Finance Corp.",
      "trackingNo":"TP-106800-29992531-9113331",
      "status":"'In Transit'",
      "consignee":"Albemarle Corporation"
   },
   {
      "orderNo":"zo-902176-72986374-2353871",
      "date":"6/1/2019",
      "customer":"Surgery Partners, Inc.",
      "trackingNo":"TP-029515-07674862-1371769",
      "status":"'In Transit'",
      "consignee":"MFS Intermediate Income Trust"
   },
   {
      "orderNo":"kf-867870-78639360-6953410",
      "date":"7/10/2019",
      "customer":"Quality Care Properties, Inc.",
      "trackingNo":"TP-966264-61844725-4014871",
      "status":"'In Transit'",
      "consignee":"Citigroup Inc."
   },
   {
      "orderNo":"fl-692772-36934030-7316700",
      "date":"7/2/2019",
      "customer":"Energy XXI Gulf Coast, Inc.",
      "trackingNo":"TP-401583-25438201-6955965",
      "status":"'Delivered'",
      "consignee":"DURECT Corporation"
   },
   {
      "orderNo":"vj-959578-73581187-3676952",
      "date":"11/21/2018",
      "customer":"Kadmon Holdings, Inc.",
      "trackingNo":"TP-024898-27451448-9504385",
      "status":"'In Transit'",
      "consignee":"Great Elm Capital Group, Inc. "
   },
   {
      "orderNo":"vo-168267-57567037-2415259",
      "date":"5/3/2019",
      "customer":"Peregrine Pharmaceuticals Inc.",
      "trackingNo":"TP-992350-42907141-7601691",
      "status":"'Shipped'",
      "consignee":"BiondVax Pharmaceuticals Ltd."
   },
   {
      "orderNo":"gy-881742-17368118-3339154",
      "date":"12/13/2018",
      "customer":"Orion Engineered Carbons S.A",
      "trackingNo":"TP-631671-75209321-2130042",
      "status":"'In Transit'",
      "consignee":"Moody's Corporation"
   },
   {
      "orderNo":"dg-963777-28868036-9183231",
      "date":"3/18/2019",
      "customer":"Comtech Telecommunications Corp.",
      "trackingNo":"TP-977411-64642228-2345749",
      "status":"'Delivered'",
      "consignee":"Statoil ASA"
   },
   {
      "orderNo":"ts-166919-87594194-9149341",
      "date":"6/12/2019",
      "customer":"Insight Select Income Fund",
      "trackingNo":"TP-353664-35544542-1493462",
      "status":"'Delivered'",
      "consignee":"Public Storage"
   },
   {
      "orderNo":"wa-228006-02108480-9709636",
      "date":"8/2/2019",
      "customer":"Transdigm Group Incorporated",
      "trackingNo":"TP-883947-22482765-0866804",
      "status":"'Delivered'",
      "consignee":"Wins Finance Holdings Inc."
   },
   {
      "orderNo":"xl-462655-43650707-2776155",
      "date":"11/14/2018",
      "customer":"New Age Beverages Corporation",
      "trackingNo":"TP-974672-34672405-7402681",
      "status":"'Delivered'",
      "consignee":"Deswell Industries, Inc."
   },
   {
      "orderNo":"eg-857637-35239970-0266484",
      "date":"11/2/2018",
      "customer":"The Cushing MLP Total Return Fund",
      "trackingNo":"TP-071375-04167196-9029019",
      "status":"'In Transit'",
      "consignee":"Ossen Innovation Co., Ltd."
   },
   {
      "orderNo":"sl-117725-93335025-1318710",
      "date":"10/8/2019",
      "customer":"Arista Networks, Inc.",
      "trackingNo":"TP-120107-30005405-3721191",
      "status":"'In Transit'",
      "consignee":"Uni-Pixel, Inc."
   },
   {
      "orderNo":"fl-480157-21452000-3719896",
      "date":"12/4/2018",
      "customer":"Vodafone Group Plc",
      "trackingNo":"TP-798493-47213937-9505426",
      "status":"'Shipped'",
      "consignee":"Western Asset Mortgage Capital Corporation"
   },
   {
      "orderNo":"tm-647973-92517510-9486274",
      "date":"11/4/2018",
      "customer":"Methanex Corporation",
      "trackingNo":"TP-491946-72508722-6384928",
      "status":"'In Transit'",
      "consignee":"Avis Budget Group, Inc."
   },
   {
      "orderNo":"xk-904121-55028111-3313950",
      "date":"5/27/2019",
      "customer":"Southern Copper Corporation",
      "trackingNo":"TP-754271-22868145-5682714",
      "status":"'Delivered'",
      "consignee":"Liberty Media Corporation"
   },
   {
      "orderNo":"rs-083223-66933113-6383147",
      "date":"12/13/2018",
      "customer":"Texas Instruments Incorporated",
      "trackingNo":"TP-635859-15449011-6058118",
      "status":"'Delivered'",
      "consignee":"Progressive Corporation (The)"
   },
   {
      "orderNo":"cn-055679-44638561-2915475",
      "date":"3/6/2019",
      "customer":"General Electric Capital Corporation",
      "trackingNo":"TP-753008-28462313-5527947",
      "status":"'Delivered'",
      "consignee":"Columbia Banking System, Inc."
   },
   {
      "orderNo":"wb-171466-56681927-5383165",
      "date":"11/23/2018",
      "customer":"Gol Linhas Aereas Inteligentes S.A.",
      "trackingNo":"TP-582629-77848455-9687997",
      "status":"'Shipped'",
      "consignee":"FlexShopper, Inc."
   },
   {
      "orderNo":"lj-906579-87509307-7835455",
      "date":"7/22/2019",
      "customer":"Parkway, Inc.",
      "trackingNo":"TP-707482-17365222-6951914",
      "status":"'Delivered'",
      "consignee":"Global Indemnity Limited"
   },
   {
      "orderNo":"kw-243926-16396376-5061486",
      "date":"6/1/2019",
      "customer":"United States Cellular Corporation",
      "trackingNo":"TP-044648-14325394-5391204",
      "status":"'Shipped'",
      "consignee":"Lifeway Foods, Inc."
   },
   {
      "orderNo":"xf-467174-29039637-6875752",
      "date":"9/7/2019",
      "customer":"Delta Technology Holdings Limited",
      "trackingNo":"TP-462081-19612662-1338898",
      "status":"'Delivered'",
      "consignee":"Intec Pharma Ltd."
   },
   {
      "orderNo":"tf-437799-04875903-2530022",
      "date":"6/1/2019",
      "customer":"Dynegy Inc.",
      "trackingNo":"TP-799509-02838621-2610402",
      "status":"'Delivered'",
      "consignee":"Essendant Inc."
   },
   {
      "orderNo":"xd-250158-81136821-2934278",
      "date":"6/1/2019",
      "customer":"Telecom Italia S.P.A.",
      "trackingNo":"TP-245592-99698259-8838620",
      "status":"'Shipped'",
      "consignee":"Aetna Inc."
   },
   {
      "orderNo":"ud-185252-30367338-8869122",
      "date":"10/4/2019",
      "customer":"Mirna Therapeutics, Inc.",
      "trackingNo":"TP-838659-11586000-7479167",
      "status":"'Delivered'",
      "consignee":"Cohen & Steers MLP Income and Energy Opportunity Fund, Inc."
   },
   {
      "orderNo":"wf-861432-78791747-0696862",
      "date":"6/28/2019",
      "customer":"Stage Stores, Inc.",
      "trackingNo":"TP-328772-25627787-9908906",
      "status":"'In Transit'",
      "consignee":"Randolph Bancorp, Inc."
   },
   {
      "orderNo":"ki-615172-80178611-1822738",
      "date":"9/7/2019",
      "customer":"Alibaba Group Holding Limited",
      "trackingNo":"TP-060350-25130986-1020132",
      "status":"'Shipped'",
      "consignee":"Assured Guaranty Ltd."
   },
   {
      "orderNo":"hb-384112-28658470-5884844",
      "date":"2/14/2019",
      "customer":"Bassett Furniture Industries, Incorporated",
      "trackingNo":"TP-951163-83842499-8603850",
      "status":"'Shipped'",
      "consignee":"Entertainment Gaming Asia Incorporated"
   },
   {
      "orderNo":"iq-958996-92357950-4209145",
      "date":"1/27/2019",
      "customer":"Lyon William Homes",
      "trackingNo":"TP-777903-31968261-4417003",
      "status":"'Shipped'",
      "consignee":"Proteon Therapeutics, Inc."
   },
   {
      "orderNo":"zg-911052-24366118-8985020",
      "date":"10/29/2018",
      "customer":"Foundation Building Materials, Inc.",
      "trackingNo":"TP-340554-16817653-8416480",
      "status":"'Delivered'",
      "consignee":"Stone Harbor Emerging Markets Income Fund"
   },
   {
      "orderNo":"in-325597-90187915-9199162",
      "date":"9/5/2019",
      "customer":"B Communications Ltd.",
      "trackingNo":"TP-599497-68797989-5846439",
      "status":"'Delivered'",
      "consignee":"TESARO, Inc."
   },
   {
      "orderNo":"va-718842-90167134-9115698",
      "date":"12/31/2018",
      "customer":"Sierra Oncology, Inc.",
      "trackingNo":"TP-483749-22683551-2368992",
      "status":"'In Transit'",
      "consignee":"TG Therapeutics, Inc."
   },
   {
      "orderNo":"ur-066678-55072989-4433872",
      "date":"8/10/2019",
      "customer":"Gentex Corporation",
      "trackingNo":"TP-363635-42647761-3036070",
      "status":"'Shipped'",
      "consignee":"Gabelli NextShares Trust"
   },
   {
      "orderNo":"cp-592136-53789597-8337296",
      "date":"4/20/2019",
      "customer":"Invuity, Inc.",
      "trackingNo":"TP-273636-61728693-3397513",
      "status":"'In Transit'",
      "consignee":"China Unicom (Hong Kong) Ltd"
   },
   {
      "orderNo":"ie-917073-24123327-0485011",
      "date":"6/6/2019",
      "customer":"Xperi Corporation",
      "trackingNo":"TP-992131-93484883-1513420",
      "status":"'Delivered'",
      "consignee":"CafePress Inc."
   },
   {
      "orderNo":"ba-937023-92575253-3020725",
      "date":"6/10/2019",
      "customer":"Weis Markets, Inc.",
      "trackingNo":"TP-292243-90724903-3026943",
      "status":"'Shipped'",
      "consignee":"Signature Bank"
   },
   {
      "orderNo":"iy-623437-16426594-1514973",
      "date":"6/12/2019",
      "customer":"Sunoco LP",
      "trackingNo":"TP-827975-93792111-2512899",
      "status":"'Delivered'",
      "consignee":"Burlington Stores, Inc."
   },
   {
      "orderNo":"le-840807-38370805-8732019",
      "date":"6/3/2019",
      "customer":"Prudential Financial, Inc.",
      "trackingNo":"TP-605010-13055788-7742845",
      "status":"'Delivered'",
      "consignee":"Cumberland Pharmaceuticals Inc."
   },
   {
      "orderNo":"mz-097224-42418194-9622035",
      "date":"12/12/2018",
      "customer":"Revolution Lighting Technologies, Inc.",
      "trackingNo":"TP-501864-64991237-2721659",
      "status":"'Shipped'",
      "consignee":"Kayne Anderson Acquisition Corp."
   },
   {
      "orderNo":"zm-536101-04294774-0233556",
      "date":"1/5/2019",
      "customer":"J. Alexander's Holdings, Inc.",
      "trackingNo":"TP-176300-08871671-3247779",
      "status":"'In Transit'",
      "consignee":"Forum Energy Technologies, Inc."
   },
   {
      "orderNo":"ba-206887-22636212-7462969",
      "date":"11/30/2018",
      "customer":"PartnerRe Ltd.",
      "trackingNo":"TP-587255-63115206-1617167",
      "status":"'Shipped'",
      "consignee":"MIND C.T.I. Ltd."
   },
   {
      "orderNo":"ud-201621-80008772-6306922",
      "date":"5/21/2019",
      "customer":"Pyxis Tankers Inc.",
      "trackingNo":"TP-291470-78316998-2040702",
      "status":"'Delivered'",
      "consignee":"Double Eagle Acquisition Corp."
   },
   {
      "orderNo":"bn-649714-41753299-0817090",
      "date":"11/8/2018",
      "customer":"Entercom Communications Corporation",
      "trackingNo":"TP-748181-59430580-9932257",
      "status":"'In Transit'",
      "consignee":"Ecology and Environment, Inc."
   },
   {
      "orderNo":"eq-158500-60339635-6278433",
      "date":"7/16/2019",
      "customer":"Open Text Corporation",
      "trackingNo":"TP-548389-03651143-6462036",
      "status":"'Delivered'",
      "consignee":"BCB Bancorp, Inc. (NJ)"
   },
   {
      "orderNo":"ti-371327-28038764-7645842",
      "date":"11/4/2018",
      "customer":"Herc Holdings Inc.",
      "trackingNo":"TP-358201-03544895-0059277",
      "status":"'In Transit'",
      "consignee":"Warrior Met Coal, Inc."
   },
   {
      "orderNo":"my-812102-66636651-7419498",
      "date":"8/2/2019",
      "customer":"CIT Group Inc (DEL)",
      "trackingNo":"TP-360038-88166724-9943252",
      "status":"'In Transit'",
      "consignee":"Northern Trust Corporation"
   },
   {
      "orderNo":"bn-516773-15087149-2764531",
      "date":"5/7/2019",
      "customer":"Liberty Interactive Corporation",
      "trackingNo":"TP-308478-70905548-7541067",
      "status":"'In Transit'",
      "consignee":"Nuvectra Corporation"
   },
   {
      "orderNo":"rw-209316-74010268-3576390",
      "date":"8/29/2019",
      "customer":"EPR Properties",
      "trackingNo":"TP-806912-86010095-6165891",
      "status":"'In Transit'",
      "consignee":"Atmos Energy Corporation"
   },
   {
      "orderNo":"hr-530441-29798209-8518710",
      "date":"8/12/2019",
      "customer":"Weyerhaeuser Company",
      "trackingNo":"TP-842522-93700993-4695854",
      "status":"'Delivered'",
      "consignee":"McCormick & Company, Incorporated"
   },
   {
      "orderNo":"qn-199339-54741458-1570234",
      "date":"5/8/2019",
      "customer":"Eagle Bulk Shipping Inc.",
      "trackingNo":"TP-532202-71997099-9180881",
      "status":"'Shipped'",
      "consignee":"Tekla Healthcare Opportunies Fund"
   },
   {
      "orderNo":"ig-103405-14233269-7997656",
      "date":"7/8/2019",
      "customer":"Diana Shipping inc.",
      "trackingNo":"TP-809114-57995538-2880078",
      "status":"'In Transit'",
      "consignee":"iShares S&P Global Timber & Forestry Index Fund"
   },
   {
      "orderNo":"hy-821540-60448873-2904110",
      "date":"4/19/2019",
      "customer":"Guidance Software, Inc.",
      "trackingNo":"TP-085088-04500246-7739088",
      "status":"'Delivered'",
      "consignee":"Corning Incorporated"
   },
   {
      "orderNo":"id-117515-79278842-7396639",
      "date":"10/16/2019",
      "customer":"FIRST REPUBLIC BANK",
      "trackingNo":"TP-982565-08286878-6083255",
      "status":"'Delivered'",
      "consignee":"Double Eagle Acquisition Corp."
   },
   {
      "orderNo":"gb-722233-39547562-7771613",
      "date":"10/13/2019",
      "customer":"Capitala Finance Corp.",
      "trackingNo":"TP-600534-81936413-8806140",
      "status":"'Shipped'",
      "consignee":"QAD Inc."
   },
   {
      "orderNo":"sb-126255-52658012-7111327",
      "date":"3/5/2019",
      "customer":"iShares MSCI UAE Capped ETF",
      "trackingNo":"TP-122896-46483695-7436316",
      "status":"'Delivered'",
      "consignee":"Arrow DWA Tactical ETF"
   },
   {
      "orderNo":"um-113439-67806175-9787544",
      "date":"8/18/2019",
      "customer":"VEREIT Inc.",
      "trackingNo":"TP-693873-30325398-1113374",
      "status":"'Shipped'",
      "consignee":"Hercules Capital, Inc."
   },
   {
      "orderNo":"gg-431559-30730485-3180413",
      "date":"6/13/2019",
      "customer":"Cenveo Inc",
      "trackingNo":"TP-573636-28075077-1203642",
      "status":"'Shipped'",
      "consignee":"WSFS Financial Corporation"
   },
   {
      "orderNo":"va-577638-42541737-4238362",
      "date":"5/26/2019",
      "customer":"Nabors Industries Ltd.",
      "trackingNo":"TP-886854-17007955-2491476",
      "status":"'Delivered'",
      "consignee":"Guaranty Federal Bancshares, Inc."
   },
   {
      "orderNo":"gb-622118-39492254-6080346",
      "date":"1/27/2019",
      "customer":"ORBCOMM Inc.",
      "trackingNo":"TP-393232-71838846-5964492",
      "status":"'In Transit'",
      "consignee":"OneMain Holdings, Inc."
   },
   {
      "orderNo":"pj-392585-82321133-2115554",
      "date":"9/11/2019",
      "customer":"Medallion Financial Corp.",
      "trackingNo":"TP-921148-91654120-0414328",
      "status":"'In Transit'",
      "consignee":"Badger Meter, Inc."
   },
   {
      "orderNo":"xr-010132-37919972-1088011",
      "date":"10/26/2018",
      "customer":"Lakeland Financial Corporation",
      "trackingNo":"TP-028760-10713942-5736831",
      "status":"'Shipped'",
      "consignee":"Huntington Bancshares Incorporated"
   },
   {
      "orderNo":"fq-699249-11457283-7383500",
      "date":"11/9/2018",
      "customer":"BLDRS Emerging Markets 50 ADR Index Fund",
      "trackingNo":"TP-062302-74751082-4064761",
      "status":"'Delivered'",
      "consignee":"Allegiance Bancshares, Inc."
   },
   {
      "orderNo":"as-087993-62598993-4502895",
      "date":"1/10/2019",
      "customer":"First Financial Corporation Indiana",
      "trackingNo":"TP-448622-88999033-5040967",
      "status":"'In Transit'",
      "consignee":"Berkshire Hills Bancorp, Inc."
   },
   {
      "orderNo":"zz-695662-85764751-4516705",
      "date":"6/30/2019",
      "customer":"Wingstop Inc.",
      "trackingNo":"TP-199212-50592725-1733407",
      "status":"'Shipped'",
      "consignee":"Electro Scientific Industries, Inc."
   },
   {
      "orderNo":"gz-746631-36312544-7048316",
      "date":"8/19/2019",
      "customer":"MiX Telematics Limited",
      "trackingNo":"TP-844267-77153544-5609484",
      "status":"'Shipped'",
      "consignee":"Select Bancorp, Inc."
   }
]